{
  "users": [
    {
      "id": "jr8w4bt",
      "nombre": "Mario",
      "apellido": "Zaccagnini",
      "email": "marioz@gmail.com",
      "password": "$2b$10$k/gNsJE85si4hRLORXJaJOxsFZtB5KS1Yal738qS8Fu5OUdF8Iomy",
      "rol": "fotografo",
      "nombreDeUsuario": "marioz",
      "localidad": "0675601001",
      "provincia": "Buenos Aires"
    },
    {
      "id": "78owmhk",
      "nombre": "Luli",
      "apellido": "Melo",
      "email": "limo@gmail.com",
      "password": "$2b$10$9wB3ktTnd4SCyJQvlUtT0uTt0YYWhU0iL14UHYs/iBcAYqn8/3obK",
      "rol": "fotografo",
      "nombreDeUsuario": "lilom",
      "localidad": "22140030",
      "provincia": "Chaco"
    },
    {
      "id": "lcraqx2",
      "nombre": "we",
      "apellido": "wefwef",
      "email": "sofi@gmail.com",
      "password": "$2b$10$M5edSp0JsQnf2O9wjGOFHusuK2SoWWS0QcpT7bd3S7puXbHqKtrkC",
      "rol": "fotografo",
      "nombreDeUsuario": "wewef",
      "localidad": "26021020",
      "provincia": "Chubut"
    },
    {
      "id": "j427o2x",
      "nombre": "Carlos23423",
      "apellido": "Cantos23423",
      "email": "carlos@hotmail.com",
      "password": "$2b$10$G94cjyc.YYWSnzY/bUlyVOcE4pfYuD6BQw7cN4AP9LhMRghH3lFRu",
      "rol": "fotografo",
      "nombreDeUsuario": "carlitos",
      "localidad": "06357110",
      "provincia": "Buenos Aires"
    },
    {
      "id": "38xa79f",
      "nombre": "Peter",
      "apellido": "Alfonso",
      "email": "peteralf@gmail.com",
      "password": "$2b$10$JpSzzklJ7zXkShplrrqGeOlQLKuCOLSNbnACmtSWftIanwPpY4mnG",
      "rol": "fotografo",
      "nombreDeUsuario": "peteralfo",
      "localidad": "58035110",
      "provincia": "Neuquén"
    },
    {
      "id": "jr9w4bt",
      "nombre": "Sergio",
      "apellido": "Pergolini",
      "email": "pergolini@gmail.com",
      "password": "$2b$10$k/gNsJE85si4hRLORXJaJOxsFZtB5KS1Yal738qS8Fu5OUdF8Iomy",
      "rol": "admin",
      "nombreDeUsuario": "Pergolini03",
      "localidad": "0675601001",
      "provincia": "Buenos Aires"
    },
    {
      "id": "cgh4uad",
      "nombre": "Julio",
      "apellido": "Track",
      "email": "polaco@hotmail.com",
      "password": "$2b$10$aqxR16q56AoGrv6rQZ5oseb5d3e5E99vBJuI1zhwnxt2GmXxybxEi",
      "rol": "fotografo",
      "nombreDeUsuario": "julito10",
      "localidad": "62084020",
      "provincia": "Río Negro"
    }
  ],
  "posts": [
    {
      "id": "1",
      "url": "https://images.unsplash.com/photo-1533683083439-1a776a5653cb?ixlib=rb-4.1.0&ixid=M3wxMjA3fDB8MHxwaG90by1wYWdlfHx8fGVufDB8fHx8fA%3D%3D&auto=format&fit=crop&q=80&w=687",
      "descripcion": "¡Increíble atardecer en las montañas! La naturaleza nunca deja de sorprenderme.",
      "ubicacion": "Patagonia, Argentina",
      "coordenadas": {
        "lat": -41.1335,
        "lng": -71.3103
      },
      "fotografo": {
        "id": "1",
        "nombre": "Ana",
        "apellido": "García",
        "email": "ana@example.com",
        "password": "",
        "rol": "fotografo",
        "nombreDeUsuario": "ana_fotografa",
        "localidad": "Bariloche",
        "provincia": "Río Negro"
      },
      "fecha": "2024-11-01T18:30:00",
      "likes": 1234
    },
    {
      "id": "2",
      "url": "https://images.unsplash.com/photo-1506905925346-21bda4d32df4",
      "descripcion": "¡Anochecer en la sierra!",
      "ubicacion": "Mendoza, Argentina",
      "coordenadas": {
        "lat": -32.8895,
        "lng": -68.8458
      },
      "fotografo": {
        "id": "2",
        "nombre": "Joaquín",
        "apellido": "Francis",
        "email": "joaco12@example.com",
        "password": "",
        "rol": "fotografo",
        "nombreDeUsuario": "joaquin-vg",
        "localidad": "Córdoba",
        "provincia": "Río Negro"
      },
      "fecha": "2025-11-01T18:20:00",
      "likes": 6325
    },
    {
      "id": "3",
      "url": "https://images.unsplash.com/photo-1759854909297-cf3fae2e90f3?ixlib=rb-4.1.0&ixid=M3wxMjA3fDB8MHxwaG90by1wYWdlfHx8fGVufDB8fHx8fA%3D%3D&auto=format&fit=crop&q=80&w=687",
      "descripcion": "El mar es mi hogar",
      "ubicacion": "Mar del Plata, Argentina",
      "coordenadas": {
        "lat": -38.0055,
        "lng": -57.5426
      },
      "fotografo": {
        "id": "3",
        "nombre": "Moncho",
        "apellido": "Peña",
        "email": "moncho@example.com",
        "password": "",
        "rol": "fotografo",
        "nombreDeUsuario": "moncho_peñoso",
        "localidad": "Mar del Plata",
        "provincia": "Buenos Aires"
      },
      "fecha": "2024-12-12T11:30:00",
      "likes": 1234323
    }
  ]
}